{
  "recipes": {
    "rabbitmq_chef": "Install and configure rabbitmq specifically for a Chef Server"
  },
  "suggestions": {
  },
  "platforms": {
    "debian": [

    ],
    "fedora": [

    ],
    "centos": [

    ],
    "ubuntu": [

    ],
    "redhat": [

    ]
  },
  "long_description": "",
  "conflicting": {
  },
  "description": "Installs the RabbitMQ AMQP Broker for use on a Chef Server.",
  "providing": {
  },
  "dependencies": {
    "erlang": [

    ]
  },
  "maintainer": "Opscode, Inc.",
  "version": "0.10.3",
  "attributes": {
  },
  "replacing": {
  },
  "maintainer_email": "cookbooks@opscode.com",
  "groupings": {
  },
  "name": "rabbitmq_chef",
  "recommendations": {
  },
  "license": "Apache 2.0"
}